{
  "schema_version": "v1",
  "name_for_model": "maven_tool",
  "name_for_human": "Maven Version Tool",
  "description_for_model": "Fetches latest stable version of a Maven package given groupId and artifactId.",
  "description_for_human": "Call this tool to get the latest version of Maven libraries.",
  "auth": {
    "type": "none"
  },
  "api": {
    "type": "openapi",
    "url": "http://localhost:8000/openapi.yaml",
    "is_user_authenticated": false
  },
  "logo_url": "https://yourdomain.com/logo.png",
  "contact_email": "you@example.com",
  "legal_info_url": "http://yourdomain.com/legal"
}
